GeoAreaCalc/__init__.py
GeoAreaCalc/area_calculator.py
GeoAreaCalc/shapes.py
tests/__init__.py
tests/test_area_calculator.py
tests/test_shapes.py
GeoAreaCalc-0.0.1.dist-info/LICENSE
GeoAreaCalc-0.0.1.dist-info/METADATA
GeoAreaCalc-0.0.1.dist-info/WHEEL
GeoAreaCalc-0.0.1.dist-info/top_level.txt
GeoAreaCalc-0.0.1.dist-info/RECORD
