Metadata-Version: 2.1
Name: GeoAreaCalc
Version: 0.0.1
Summary: This library calculates the area of shapes
Home-page: https://github.com/Qiaxx/GeoAreaCalc
Author: Qiaxx
Author-email: belozertsev04@mail.ru
Project-URL: GitHub, https://github.com/Qiaxx/GeoAreaCalc
Keywords: calculate,area,geometry,shape
Classifier: Programming Language :: Python :: 3.12
Classifier: License :: OSI Approved :: MIT License
Classifier: Operating System :: OS Independent
Requires-Python: ==3.12
License-File: LICENSE
